py_konf/__init__.py
py_konf/cli.py
py_konf/config.py
py_konf/sources/__init__.py
py_konf/sources/base.py
py_konf/sources/cli.py
py_konf/sources/envvars.py
py_konf/sources/files.py
py_konf/sources/prompt.py
py_konf/test/__init__.py
py_konf/test/conftest.py
py_konf/test/sources/__init__.py
py_konf/test/sources/test_cli.py
py_konf/test/sources/test_envvars.py
py_konf/test/sources/test_files.py
py_konf/test/sources/test_prompt.py
py_konf/test/test_cli.py
py_konf/test/test_config.py
py_konf/value.py
py_konf-0.1.3.dist-info/WHEEL
py_konf-0.1.3.dist-info/METADATA
py_konf-0.1.3.dist-info/RECORD
