Metadata-Version: 2.1
Name: py-konf
Version: 0.1.3
Summary: Simple lib for loading run configurations
Author: Jordan Paoletti
Author-email: jordanspaoletti@gmail.com
Requires-Python: >=3.10,<4.0
Classifier: Programming Language :: Python :: 3
Classifier: Programming Language :: Python :: 3.10
Classifier: Programming Language :: Python :: 3.11
